LICENSE
MANIFEST.in
README.md
requirements.txt
setup.py
couchdiscover/__init__.py
couchdiscover/config.py
couchdiscover/couch.py
couchdiscover/entrypoints.py
couchdiscover/exceptions.py
couchdiscover/kube.py
couchdiscover/manage.py
couchdiscover/util.py
couchdiscover.egg-info/PKG-INFO
couchdiscover.egg-info/SOURCES.txt
couchdiscover.egg-info/dependency_links.txt
couchdiscover.egg-info/entry_points.txt
couchdiscover.egg-info/not-zip-safe
couchdiscover.egg-info/requires.txt
couchdiscover.egg-info/top_level.txt
tasks/__init__.py
tasks/docker.py
tasks/py.py
tasks/test.py