Metadata-Version: 1.1
Name: couchdiscover
Version: 0.2.4
Summary: Autodiscovery & Clustering for CouchDB 2.0 with Kubernetes
Home-page: https://github.com/joeblackwaslike/couchdiscover
Author: Joe Black
Author-email: joeblack949@gmail.com
License: Apache 2.0
Download-URL: https://github.com/joeblackwaslike/couchdiscover/tarball/0.2.4
Keywords: couchdb,kubernetes,cluster
Platform: UNKNOWN
Classifier: Development Status :: 3 - Alpha
Classifier: Intended Audience :: Developers
Classifier: Operating System :: OS Independent
Classifier: Natural Language :: English
Classifier: License :: OSI Approved :: Apache Software License
Classifier: Programming Language :: Python :: 3 :: Only
Classifier: Topic :: Database
Classifier: Topic :: Internet :: WWW/HTTP
Classifier: Topic :: System :: Clustering
